lx/__init__.py
lx/object.py
lx/result.py
lx/service.py
lx/symbol.py
lxguid/__init__.py
lxifc/__init__.py
lxserv/__init__.py
lxu/__init__.py
lxu/attrdesc.py
lxu/attributes.py
lxu/chanmod.py
lxu/command.py
lxu/object.py
lxu/package.py
lxu/select.py
lxu/service.py
lxu/utils.py
lxu/vector.py
lxu/meta/__init__.py
lxu/meta/chanmod.py
lxu/meta/channel.py
lxu/meta/command.py
lxu/meta/drop.py
lxu/meta/falloff.py
lxu/meta/meta.py
lxu/meta/modifier.py
lxu/meta/package.py
lxu/meta/schematic.py
lxu/meta/select.py
modo/__init__.py
modo/channel.py
modo/constants.py
modo/dialogs.py
modo/item.py
modo/mathutils.py
modo/meshgeometry.py
modo/mprop.py
modo/scene.py
modo/util.py
modo_api-15.1.2.dist-info/LICENSE
modo_api-15.1.2.dist-info/METADATA
modo_api-15.1.2.dist-info/WHEEL
modo_api-15.1.2.dist-info/top_level.txt
modo_api-15.1.2.dist-info/RECORD
